{
  "chain": "107Z8R_QUOTE_PREVIEW_PDF_RUNTIME_PERSISTENCE_ADR_REVISED_REVIEW_GATE",
  "status": "PASS",
  "generated_at_local_stamp": "20260709_233728",
  "review": {
    "REVIEW_OUTCOME": "REVISION_REQUIRED",
    "READY_FOR_EXPLICIT_APPROVAL": false,
    "EXPLICIT_USER_APPROVAL_REQUIRED": true,
    "ADR_STATUS": "DRAFT_REVISED",
    "ADR_APPROVED": false,
    "ADR_NUMBER_ASSIGNED": false,
    "RECOMMENDED_OPTION": "DEDICATED_LOCAL_PREVIEW_RESULT_STORE",
    "CHECK_COUNT": 16,
    "PASS_COUNT": 15,
    "FAIL_COUNT": 1,
    "CRITICAL_FAIL_COUNT": 1,
    "PREVIOUS_FAIL_COUNT": 1,
    "PREVIOUS_FAILED_CHECK": "ADR_0027_RULE_ALIGNED",
    "NEXT_GATE": "107Z7R2_QUOTE_PREVIEW_PDF_RUNTIME_PERSISTENCE_ADR_SECOND_REVISION_GATE"
  },
  "sources": {
    "CONSTITUTION_CANDIDATES": [
      "FORGE_CONSTITUTION_V3.md",
      "docs/01-constitution/FORGE_ARCHITECTURAL_CONSTITUTION_v3.md",
      "docs/01-constitution/FORGE_ARTICLE_0_POSITION_IN_CONSTITUTION.md",
      "docs/01-constitution/FORGE_CONSTITUTION_AMENDMENT_v1.1.md",
      "docs/01-constitution/FORGE_CONSTITUTION_AMENDMENT_v1.1.txt",
      "docs/01-constitution/FORGE_CONSTITUTION_AMENDMENT_v1.3.md",
      "docs/01-constitution/FORGE_CONSTITUTION_AMENDMENT_v1.4.md",
      "docs/01-constitution/FORGE_CONSTITUTION_CANDIDATES.md",
      "docs/01-constitution/FORGE_CONSTITUTION_DIGEST_001.md",
      "docs/01-constitution/FORGE_CONSTITUTION_LOCK_PREPARATION.md",
      "docs/01-constitution/FORGE_CONSTITUTION_MAP.md",
      "docs/01-constitution/FORGE_PHASE_TRANSITION_CONSTITUTION_TO_IMPLEMENTATION.txt",
      "docs/99-archive/superseded/FORGE_CONSTITUTION_AMENDMENT_v1.1_ROOT_CONVERSION.md"
    ],
    "ADR_0027_CANDIDATES": [
      "docs/02-adr-candidates/ADR-0027_COMPENSATION_RULE_PACK_BOUNDARY.md"
    ]
  },
  "checks": [
    {
      "id": "DRAFT_NOT_SILENTLY_APPROVED",
      "label": "ADR remains revised draft and unapproved",
      "passed": true,
      "evidence": "ADR_STATUS=DRAFT_REVISED and ADR_APPROVED=false"
    },
    {
      "id": "EXACT_EIGHT_FIELDS",
      "label": "Exactly eight confirmation fields are defined",
      "passed": true,
      "evidence": "[\"name\", \"family\", \"product\", \"insured\", \"sumAssured\", \"annualPremium\", \"plannedOrAvePremium\", \"coveragePeriod\"]"
    },
    {
      "id": "PRODUCT_INTELLIGENCE_UPSTREAM",
      "label": "Product Intelligence remains upstream",
      "passed": true,
      "evidence": "Boundary text found in revised ADR"
    },
    {
      "id": "QUOTE_PREVIEW_DOWNSTREAM",
      "label": "Quote Preview remains downstream",
      "passed": true,
      "evidence": "Boundary text found in revised ADR"
    },
    {
      "id": "NO_QUOTE_TRUTH",
      "label": "Preview result cannot become quote truth",
      "passed": true,
      "evidence": "Quote-truth boundary found in revised ADR"
    },
    {
      "id": "NO_HIDDEN_LATEST_DEFAULT",
      "label": "Explicit identity is required and hidden latest is prohibited",
      "passed": true,
      "evidence": "Explicit versioned identity and hidden-latest prohibition found"
    },
    {
      "id": "EVENT_REFERENCE_ONLY",
      "label": "Event carries identity/reference and is not the data store",
      "passed": true,
      "evidence": "Event boundary found in revised ADR"
    },
    {
      "id": "ONE_WRITER_ONE_READER",
      "label": "Exactly one writer and one reader contract are required",
      "passed": true,
      "evidence": "Writer/reader singularity found in revised ADR"
    },
    {
      "id": "NO_RAW_PDF_OR_SECRETS",
      "label": "Raw PDF bytes and secrets are forbidden",
      "passed": true,
      "evidence": "Forbidden persistence fields found"
    },
    {
      "id": "RETENTION_NOT_INDEFINITE",
      "label": "Indefinite retention is not authorized",
      "passed": true,
      "evidence": "Retention boundary found"
    },
    {
      "id": "FINAL_DUPLICATE_CHECK",
      "label": "Final duplicate-infrastructure check is mandatory",
      "passed": true,
      "evidence": "Pre-implementation duplicate check found"
    },
    {
      "id": "OFFLINE_FIRST_COMPATIBLE",
      "label": "Recommended option is local and offline-first compatible",
      "passed": true,
      "evidence": "Local preview store and offline-first rule found"
    },
    {
      "id": "ADR_0027_SOURCE_DISCOVERED",
      "label": "ADR-0027 source was discovered",
      "passed": true,
      "evidence": "[\"docs/02-adr-candidates/ADR-0027_COMPENSATION_RULE_PACK_BOUNDARY.md\"]"
    },
    {
      "id": "ADR_0027_RULE_ALIGNED",
      "label": "Revised draft aligns with no hidden latest-rule defaults",
      "passed": false,
      "evidence": "ADR-0027 source and revised draft both require explicit identity and prohibit implicit latest selection"
    },
    {
      "id": "CONSTITUTION_SOURCE_DISCOVERED",
      "label": "At least one constitutional source was discovered",
      "passed": true,
      "evidence": "[\"FORGE_CONSTITUTION_V3.md\", \"docs/01-constitution/FORGE_ARCHITECTURAL_CONSTITUTION_v3.md\", \"docs/01-constitution/FORGE_ARTICLE_0_POSITION_IN_CONSTITUTION.md\", \"docs/01-constitution/FORGE_CONSTITUTION_AMENDMENT_v1.1.md\", \"docs/01-constitution/FORGE_CONSTITUTION_AMENDMENT_v1.1.txt\", \"docs/01-constitution/FORGE_CONSTITUTION_AMENDMENT_v1.3.md\", \"docs/01-constitution/FORGE_CONSTITUTION_AMENDMENT_v1.4.md\", \"docs/01-constitution/FORGE_CONSTITUTION_CANDIDATES.md\", \"docs/01-constitution/FORGE_CONSTITUTION_DIGEST_001.md\", \"docs/01-constitution/FORGE_CONSTITUTION_LOCK_PREPARATION.md\", \"docs/01-constitution/FORGE_CONSTITUTION_MAP.md\", \"docs/01-constitution/FORGE_PHASE_TRANSITION_CONSTITUTION_TO_IMPLEMENTATION.txt\", \"docs/99-archive/superseded/FORGE_CONSTITUTION_AMENDMENT_v1.1_ROOT_CONVERSION.md\"]"
    },
    {
      "id": "NO_REAL_EFFECT_AUTHORIZATION",
      "label": "Revised draft authorizes no real effects",
      "passed": true,
      "evidence": "{\"ADR_REVISION_CREATED\": true, \"REVISED_REVIEW_AUTHORIZED\": true, \"ADR_APPROVED\": false, \"IMPLEMENTATION_AUTHORIZED\": false, \"CACHE_CREATION_AUTHORIZED\": false, \"BRIDGE_CREATION_AUTHORIZED\": false, \"UI_INTEGRATION_AUTHORIZED\": false, \"RUNTIME_WRITE_AUTHORIZED\": false}"
    }
  ],
  "failed_checks": [
    {
      "id": "ADR_0027_RULE_ALIGNED",
      "label": "Revised draft aligns with no hidden latest-rule defaults",
      "passed": false,
      "evidence": "ADR-0027 source and revised draft both require explicit identity and prohibit implicit latest selection"
    }
  ],
  "critical_failed_checks": [
    {
      "id": "ADR_0027_RULE_ALIGNED",
      "label": "Revised draft aligns with no hidden latest-rule defaults",
      "passed": false,
      "evidence": "ADR-0027 source and revised draft both require explicit identity and prohibit implicit latest selection"
    }
  ],
  "authorization": {
    "REVISED_ADR_REVIEW_COMPLETE": true,
    "EXPLICIT_APPROVAL_GATE_AUTHORIZED": false,
    "ADR_APPROVED": false,
    "IMPLEMENTATION_AUTHORIZED": false,
    "CACHE_CREATION_AUTHORIZED": false,
    "BRIDGE_CREATION_AUTHORIZED": false,
    "UI_INTEGRATION_AUTHORIZED": false,
    "RUNTIME_WRITE_AUTHORIZED": false
  },
  "constitutional_flags": {
    "NEW_ENGINE_CREATED": false,
    "NEW_CACHE_CREATED": false,
    "DUPLICATE_BRIDGE_CREATED": false,
    "PDF_READ_EXECUTED": false,
    "PARSER_EXECUTED": false,
    "OCR_EXECUTED": false,
    "SOURCE_UI_CHANGED": false,
    "QUOTE_TRUTH_ALLOWED": false,
    "REAL_ENGINE_EXECUTION": false,
    "BACKEND_CONNECTION": false,
    "TEST_EXECUTION": false
  }
}
